{
  "tasks": [
    {
      "id": 5,
      "title": "task3",
      "description": "29th jan,2022",
      "urgency": "medium",
      "status": "Backlog",
      "isCollapsed": true
    },
    {
      "title": "work",
      "deadline": "26jan",
      "urgency": "medium",
      "status": "Backlog",
      "isCollapsed": "true",
      "id": 6
    },
    {
      "title": "work4",
      "deadline": "27th jan",
      "urgency": "medium",
      "status": "Backlog",
      "isCollapsed": "true",
      "id": 7
    },
    {
      "title": "abhishek",
      "deadline": "29th jan",
      "urgency": "low",
      "status": "Backlog",
      "isCollapsed": "true",
      "id": 8
    }
  ]
}